salesmanago_python_api/__init__.py
salesmanago_python_api-0.1.dist-info/DESCRIPTION.rst
salesmanago_python_api-0.1.dist-info/METADATA
salesmanago_python_api-0.1.dist-info/metadata.json
salesmanago_python_api-0.1.dist-info/RECORD
salesmanago_python_api-0.1.dist-info/top_level.txt
salesmanago_python_api-0.1.dist-info/WHEEL
salesmanago_python_api-0.1.dist-info/zip-safe
