Metadata-Version: 2.0
Name: salesmanago-python-api
Version: 0.1
Summary: Client for Salesmanago API.
Home-page: https://github.com/haloween/salesmanago-python-api
Author: Tomasz Utracki-Janeta
Author-email: halgravity+githubrepo@gmail.com
License: MIT
Keywords: salesmanago,api
Platform: UNKNOWN
Classifier: Development Status :: 4 - Beta
Classifier: Intended Audience :: Developers
Classifier: License :: OSI Approved :: MIT License
Classifier: Programming Language :: Python :: 3.7
Classifier: Programming Language :: Python :: 3.8
Requires-Dist: requests
